lambda_harness/__init__.py
lambda_harness/_version.py
lambda_harness/cli.py
lambda_harness/extractor.py
lambda_harness/slicer.py
lambda_harness/awslambda/__init__.py
lambda_harness/awslambda/bootstrap.py
lambda_harness/awslambda/runtime.py
lambda_harness/awslambda/wsgi.py
lambda_harness-1.3.1.dist-info/DESCRIPTION.rst
lambda_harness-1.3.1.dist-info/METADATA
lambda_harness-1.3.1.dist-info/RECORD
lambda_harness-1.3.1.dist-info/WHEEL
lambda_harness-1.3.1.dist-info/entry_points.txt
lambda_harness-1.3.1.dist-info/metadata.json
lambda_harness-1.3.1.dist-info/top_level.txt
