Metadata-Version: 2.0
Name: lambda-harness
Version: 1.3.1
Summary: Test harness for AWS Lambda
Home-page: https://github.com/brandond/lambda-harness
Author: Brandon Davidson
Author-email: brad@oatmail.org
License: Copyright 2016 Brandon Davidson
Requires-Dist: awscli
Requires-Dist: boto3
Requires-Dist: botocore
Requires-Dist: click
